{
  "name": "Classification Callback",
  "nodes": [
    {
      "parameters": {
        "httpMethod": "POST",
        "path": "job-classification-complete",
        "options": {}
      },
      "type": "n8n-nodes-base.webhook",
      "typeVersion": 2.1,
      "position": [
        2080,
        144
      ],
      "id": "74a68140-9757-40c5-9628-c6db78b9aca0",
      "name": "Classification Complete",
      "webhookId": "job-classification-complete"
    },
    {
      "parameters": {
        "method": "POST",
        "url": "http://<job-pipeline-service-host>:8000/applications/generate/run",
        "sendBody": true,
        "specifyBody": "json",
        "jsonBody": "={{ { \"user_id\": 1, \"limit\": 100, \"resume_strategy\": \"default_fallback\" } }}",
        "options": {}
      },
      "type": "n8n-nodes-base.httpRequest",
      "typeVersion": 4.4,
      "position": [
        2464,
        144
      ],
      "id": "eb73b2dc-6f22-46e9-93c9-e03878d5aa87",
      "name": "Generate Applications"
    },
    {
      "parameters": {
        "method": "POST",
        "url": "http://<job-pipeline-service-host>:8000/applications/score/run",
        "sendBody": true,
        "specifyBody": "json",
        "jsonBody": "={{ { \"limit\": 100, \"status\": \"new\", \"force\": false, \"callback_url\": \"https://<n8n-host>/webhook/application-score-complete\" } }}",
        "options": {}
      },
      "type": "n8n-nodes-base.httpRequest",
      "typeVersion": 4.4,
      "position": [
        2816,
        144
      ],
      "id": "3d0eb6aa-1df5-4be9-ae21-fd7b0e5febd3",
      "name": "Queue Application Scoring"
    },
    {
      "parameters": {},
      "type": "n8n-nodes-base.manualTrigger",
      "typeVersion": 1,
      "position": [
        2080,
        -32
      ],
      "id": "b4dce6a9-211d-4580-bd8a-8a40f13f09f5",
      "name": "When clicking ‘Execute workflow’"
    }
  ],
  "pinData": {},
  "connections": {
    "Classification Complete": {
      "main": [
        [
          {
            "node": "Generate Applications",
            "type": "main",
            "index": 0
          }
        ]
      ]
    },
    "Generate Applications": {
      "main": [
        [
          {
            "node": "Queue Application Scoring",
            "type": "main",
            "index": 0
          }
        ]
      ]
    },
    "When clicking ‘Execute workflow’": {
      "main": [
        [
          {
            "node": "Generate Applications",
            "type": "main",
            "index": 0
          }
        ]
      ]
    }
  },
  "active": false,
  "settings": {
    "executionOrder": "v1",
    "binaryMode": "separate",
    "availableInMCP": false
  },
  "versionId": "callback-classification-complete",
  "meta": {
    "templateCredsSetupCompleted": true,
    "instanceId": ""
  },
  "id": "K4mP8qLs2R0fWd7n",
  "tags": []
}
